new_pyproject/__init__.py
new_pyproject/code.py
new_pyproject-0.1.9.dist-info/WHEEL
new_pyproject-0.1.9.dist-info/METADATA
new_pyproject-0.1.9.dist-info/RECORD
