Metadata-Version: 2.1
Name: new_pyproject
Version: 0.1.9
Summary: Project template for pypi packages & RTD docs
Keywords: python,packages,pypi,RTD,Sphinx
Author: Mike Knerr
Requires-Python: >=3.6
Classifier: Programming Language :: Python :: 3
Classifier: License :: OSI Approved :: MIT License
Classifier: Operating System :: OS Independent
Project-URL: homepage, https://github.com/mkner/new-pyproject/
